simnets/__init__.py
simnets/keras.py
simnets/ops/__init__.py
simnets/ops/libmex_dims_helper.so
simnets/ops/mex.py
simnets/ops/similarity.py
simnets/ops/simnet_ops.so
simnets/test/__init__.py
simnets/test/keras/__init__.py
simnets/unsupervised/__init__.py
simnets/unsupervised/gmm.py
simnets/unsupervised/kmeans.py
simnets/unsupervised/pca.py
simnets-0.0.1.dist-info/DESCRIPTION.rst
simnets-0.0.1.dist-info/METADATA
simnets-0.0.1.dist-info/RECORD
simnets-0.0.1.dist-info/WHEEL
simnets-0.0.1.dist-info/metadata.json
simnets-0.0.1.dist-info/top_level.txt
