Metadata-Version: 2.0
Name: simnets
Version: 0.0.1
Summary: SimNets implementation in tensorflow
Home-page: https://github.com/HUJI-Deep/simnets-tf
Author: Elhanan Ilani
Author-email: elhanan.ilani@gmail.com
License: MIT
Keywords: tensorflow simnets machine-learning
Platform: UNKNOWN
Classifier: Development Status :: 3 - Alpha
Classifier: Intended Audience :: Developers
Classifier: Topic :: Scientific/Engineering
Classifier: License :: OSI Approved :: MIT License
Classifier: Programming Language :: Python :: 3.5
Classifier: Programming Language :: C++
Classifier: Programming Language :: Python :: Implementation :: CPython
Classifier: Operating System :: POSIX :: Linux
Requires-Dist: tensorflow-gpu
Requires-Dist: keras
